skill_ovos_somafm/CHANGELOG.md
skill_ovos_somafm/LICENSE
skill_ovos_somafm/MANIFEST.in
skill_ovos_somafm/README.md
skill_ovos_somafm/__init__.py
skill_ovos_somafm/requirements.txt
skill_ovos_somafm/version.py
skill_ovos_somafm/locale/en-us/radio.voc
skill_ovos_somafm/locale/en-us/skill.json
skill_ovos_somafm/locale/en-us/somafm.voc
skill_ovos_somafm/locale/en-us/somafm_skill.voc
skill_ovos_somafm/locale/eu/radio.voc
skill_ovos_somafm/locale/eu/somafm.voc
skill_ovos_somafm/locale/gl-es/radio.voc
skill_ovos_somafm/locale/gl-es/somafm.voc
skill_ovos_somafm/ovos_skill_somafm.egg-info/PKG-INFO
skill_ovos_somafm/ovos_skill_somafm.egg-info/SOURCES.txt
skill_ovos_somafm/ovos_skill_somafm.egg-info/dependency_links.txt
skill_ovos_somafm/ovos_skill_somafm.egg-info/entry_points.txt
skill_ovos_somafm/ovos_skill_somafm.egg-info/requires.txt
skill_ovos_somafm/ovos_skill_somafm.egg-info/top_level.txt
skill_ovos_somafm/res/somafm.png
ovos_skill_somafm-0.1.5.dist-info/LICENSE
ovos_skill_somafm-0.1.5.dist-info/METADATA
ovos_skill_somafm-0.1.5.dist-info/WHEEL
ovos_skill_somafm-0.1.5.dist-info/entry_points.txt
ovos_skill_somafm-0.1.5.dist-info/top_level.txt
ovos_skill_somafm-0.1.5.dist-info/RECORD
