Metadata-Version: 2.1
Name: ovos-skill-somafm
Version: 0.1.5
Summary: ovos somafm skill plugin
Home-page: https://github.com/OpenVoiceOS/skill-ovos-somafm
Author: JarbasAi
Author-email: jarbasai@mailfence.com
License: Apache-2.0
Keywords: ovos skill plugin
Platform: UNKNOWN
Requires-Dist: ovos-utils>=0.0.38
Requires-Dist: ovos-bus-client>=0.1.0
Requires-Dist: ovos-workshop>=0.0.16
Requires-Dist: radiosoma>=0.0.1,~=0.0
